out_sim/__init__.py
out_sim/bad_sim.py
outlier_simran-0.0.1.dist-info/LICENSE
outlier_simran-0.0.1.dist-info/METADATA
outlier_simran-0.0.1.dist-info/WHEEL
outlier_simran-0.0.1.dist-info/top_level.txt
outlier_simran-0.0.1.dist-info/RECORD
