Metadata-Version: 2.1
Name: outlier-simran
Version: 0.0.1
Summary: A python package to implement outliers by interquartile
Home-page: https://github.com/pypa/outlier
Author: Simranpreet kaur
Author-email: skaur_be17@thapar.edu
License: UNKNOWN
Platform: UNKNOWN
Classifier: Programming Language :: Python :: 3
Classifier: License :: OSI Approved :: MIT License
Classifier: Operating System :: OS Independent
Requires-Python: >=3
Requires-Dist: requests
